xst_cuc_xst/__init__.py
xst_cuc_xst/server.py
xst_cuc_xst-1.0.0.dist-info/licenses/LICENSE
xst_cuc_xst-1.0.0.dist-info/METADATA
xst_cuc_xst-1.0.0.dist-info/WHEEL
xst_cuc_xst-1.0.0.dist-info/entry_points.txt
xst_cuc_xst-1.0.0.dist-info/top_level.txt
xst_cuc_xst-1.0.0.dist-info/RECORD
