Metadata-Version: 2.4
Name: xst-cuc-xst
Version: 1.0.0
Summary: MCP Server implementation providing current time functionality with timezone support
Home-page: https://github.com/yourusername/xst-cuc-xst
Author: Your Name
Author-email: your.email@example.com
Project-URL: Source, https://github.com/yourusername/xst-cuc-xst
Project-URL: Documentation, https://github.com/yourusername/xst-cuc-xst/README.md
Project-URL: Issues, https://github.com/yourusername/xst-cuc-xst/issues
Keywords: mcp model-context-protocol server time timezone
Classifier: Development Status :: 4 - Beta
Classifier: Intended Audience :: Developers
Classifier: Topic :: Software Development :: Libraries :: Python Modules
Classifier: License :: OSI Approved :: MIT License
Classifier: Programming Language :: Python :: 3
Classifier: Programming Language :: Python :: 3.7
Classifier: Programming Language :: Python :: 3.8
Classifier: Programming Language :: Python :: 3.9
Classifier: Programming Language :: Python :: 3.10
Classifier: Programming Language :: Python :: 3.11
Classifier: Operating System :: OS Independent
Requires-Python: >=3.7
License-File: LICENSE
Provides-Extra: dev
Requires-Dist: pytest>=3.7; extra == "dev"
Requires-Dist: twine>=1.15; extra == "dev"
Requires-Dist: wheel>=0.34; extra == "dev"
Dynamic: author
Dynamic: author-email
Dynamic: classifier
Dynamic: description
Dynamic: description-content-type
Dynamic: home-page
Dynamic: keywords
Dynamic: license-file
Dynamic: project-url
Dynamic: provides-extra
Dynamic: requires-python
Dynamic: summary
